bigdl/__init__.py
bigdl/friesian/__init__.py
bigdl/friesian/feature/__init__.py
bigdl/friesian/feature/table.py
bigdl/friesian/feature/utils.py
bigdl/friesian/models/__init__.py
bigdl/friesian/models/tfrs_model.py
bigdl/share/friesian/lib/bigdl-friesian-spark_3.2.1-2.1.0-SNAPSHOT-jar-with-dependencies.jar
bigdl_friesian_spark321-2.1.0b202207291.dist-info/METADATA
bigdl_friesian_spark321-2.1.0b202207291.dist-info/WHEEL
bigdl_friesian_spark321-2.1.0b202207291.dist-info/dependency_links.txt
bigdl_friesian_spark321-2.1.0b202207291.dist-info/top_level.txt
bigdl_friesian_spark321-2.1.0b202207291.dist-info/RECORD
